core/__init__.py
core/spam.py
vk_spammer-1.2.5.3.dist-info/METADATA
vk_spammer-1.2.5.3.dist-info/WHEEL
vk_spammer-1.2.5.3.dist-info/entry_points.txt
vk_spammer-1.2.5.3.dist-info/top_level.txt
vk_spammer-1.2.5.3.dist-info/RECORD
