Metadata-Version: 2.1
Name: vk-spammer
Version: 1.2.5.3
Summary: UNKNOWN
Home-page: https://github.com/fgRuslan/vk-spammer
Author: fgRuslan
Author-email: ubijca16@gmail.com
License: UNKNOWN
Platform: UNKNOWN
Requires-Dist: vk-api
Requires-Dist: python3-anticaptcha
Requires-Dist: requests
